PyBypass/__init__.py
PyBypass/__version__.py
PyBypass/main.py
PyBypass/Additional/__init__.py
PyBypass/Additional/reCaptchaV2.py
PyBypass/Additional/reCaptchaV3.py
PyBypass/Constants/__init__.py
PyBypass/Constants/regex.py
PyBypass/Constants/supported_website.py
PyBypass/Filehoster/__init__.py
PyBypass/Filehoster/anonfiles_bypass.py
PyBypass/Filehoster/antfiles_bypass.py
PyBypass/Filehoster/fichier_bypass.py
PyBypass/Filehoster/gofile_bypass.py
PyBypass/Filehoster/hxfile_bypass.py
PyBypass/Filehoster/krakenfiles_bypass.py
PyBypass/Filehoster/mdisk_bypass.py
PyBypass/Filehoster/mediafire_bypass.py
PyBypass/Filehoster/pixeldrain_bypass.py
PyBypass/Filehoster/racaty_bypass.py
PyBypass/Filehoster/sendcm_bypass.py
PyBypass/Filehoster/sfile_bypass.py
PyBypass/Filehoster/solidfiles_bypass.py
PyBypass/Filehoster/sourceforge_bypass.py
PyBypass/Filehoster/uploadbaz_bypass.py
PyBypass/Filehoster/uploadee_bypass.py
PyBypass/Filehoster/uppit_bypass.py
PyBypass/Filehoster/userscloud_bypass.py
PyBypass/Filehoster/wetransfer_bypass.py
PyBypass/Filehoster/yandex_bypass.py
PyBypass/Filehoster/zippyshare_bypass.py
PyBypass/GdriveSharer/__init__.py
PyBypass/GdriveSharer/appdrive_bypass.py
PyBypass/GdriveSharer/gdtot_bypass.py
PyBypass/GdriveSharer/hubdrive_bypass.py
PyBypass/GdriveSharer/sharerpw_bypass.py
PyBypass/Shortners/__init__.py
PyBypass/Shortners/adfly_bypass.py
PyBypass/Shortners/bitly_bypass.py
PyBypass/Shortners/gplinks_bypass.py
PyBypass/Shortners/gtlinks_bypass.py
PyBypass/Shortners/hypershort_bypass.py
PyBypass/Shortners/linkvertise_bypass.py
PyBypass/Shortners/ouo_bypass.py
PyBypass/Shortners/pkin_bypass.py
PyBypass/Shortners/shareus_bypass.py
PyBypass/Shortners/shortest_bypass.py
PyBypass/Shortners/shortly_bypass.py
PyBypass/Shortners/shortner_type_one_bypass.py
PyBypass/Shortners/shortner_type_two_bypass.py
PyBypass/Shortners/sirigan_bypass.py
PyBypass/Shortners/thinfi_bypass.py
PyBypass/Shortners/tinyurl_bypass.py
PyBypass/Shortners/try2link_bypass.py
PyBypass-2.0.1.dist-info/LICENSE
PyBypass-2.0.1.dist-info/METADATA
PyBypass-2.0.1.dist-info/WHEEL
PyBypass-2.0.1.dist-info/top_level.txt
PyBypass-2.0.1.dist-info/zip-safe
PyBypass-2.0.1.dist-info/RECORD
