Metadata-Version: 2.1
Name: PyBypass
Version: 2.0.1
Summary: Python module for bypassing different kind of links.
Home-page: UNKNOWN
Author: Sanjit Sinha
Author-email: sanjitsinha@anipirates.eu.org
License: MIT
Keywords: bypasser,ads,shortners,filehosters,gdtot,appdrive,shortners
Platform: UNKNOWN
Classifier: Programming Language :: Python :: 3
Classifier: License :: OSI Approved :: MIT License
Classifier: Operating System :: OS Independent
Requires-Python: >=3.8, <4
